{"name":"Perdomo - 30th Anniversary Box-Pressed Sun Grown - Epicure","url":"https://www.cigarcentury.com/en/cigars/perdomo-30th-anniversary-box-pressed-sun-grown-ep","brand":"Perdomo, 30th Anniversary Box-Pressed Sun Grown","series":"","diameter_mm":0,"ring":54,"length_mm":152,"length_inch":0,"format":"Toro","maker":"Tabacalera Perdomo","manufactureOrigin":"Nicaragua","isBoxpressed":true,"wrapperOrigin":["Nicaraguan Sun Grown"],"fillerOrigin":["Nicaragua"],"binderOrigin":["Nicaragua"],"color":"Colorado Maduro","aromaProfileCommunity":{"weights":{"Caramel":0.2,"Leather":0.2,"Marshmallow":0.2,"Nutmeg":0.2,"Oak":0.2},"numberOfVotes":0},"strength":"Medium To Full","price":0,"additionalNotes":"Nick Perdomo is the founder of Perdomo Cigars and the man responsible for creating an extensive portfolio of blends that are well-made, well-priced and exceptionally popular among cigar lovers. High quality control standards and consistently rich flavors with an attractive range of strengths have made Perdomo a requested brand. With several wrapper varieties to choose from, Perdomo has a distinct blend for every palate. ","specializedRatings":[{"who":"Cigar Insider","year":"2024","ratingOutOf100":93},{"who":"Cigar Coop","year":"2024","ratingOutOf100":90},{"who":"The Cigar Authority","year":"2024","ratingOutOf100":92}]}
