{"name":"Casa Magna - Domus Magnus II - Optimus","url":"https://www.cigarcentury.com/en/cigars/casa-magna-domus-magnus-ii-optimus","brand":"Casa Magna, Domus Magnus II","series":"","diameter_mm":0,"ring":52,"length_mm":146,"length_inch":0,"format":"Robusto","maker":"Plasencia Cigars","manufactureOrigin":"Nicaragua","isBoxpressed":true,"wrapperOrigin":["Nicaraguan"],"fillerOrigin":["Nicaragua"],"binderOrigin":["Nicaragua"],"color":"Maduro","aromaProfileCommunity":{"weights":{"Cedar":0.25,"Cocoa":0.25,"Nuts":0.25,"Pepper":0.25},"numberOfVotes":0},"strength":"Full","price":0,"additionalNotes":"Another beauty from industry legend Manuel Quesada, Casa Magna D. Magnus II, displays its opulence with a premium selection of the best aged 100% Nicaraguan tobaccos. Dressed in a deep brown and very oily wrapper from the fertile Jalapa region, this slow burning, medium to full body gem delivers lush top notes of pepper and cedar flavors highlighted with subtle notes of cocoa and nuts.","specializedRatings":[{"who":"Cigar Public","year":"2023","ratingOutOf100":86},{"who":"Cigar Coop","year":"2013","ratingOutOf100":93},{"who":"Halfwheel","year":"2011","ratingOutOf100":93}]}
