{"name":"CAO - Flavours - Eileen's Dream - Corona","url":"https://www.cigarcentury.com/en/cigars/cao-flavours-eileens-dream-corona","brand":"CAO, Flavours, Eileen's Dream","series":"","diameter_mm":0,"ring":42,"length_mm":133,"length_inch":0,"format":"Petit Corona","maker":"General Cigars/ ST Group","manufactureOrigin":"Dominican Republic","isBoxpressed":false,"wrapperOrigin":["Cameroon"],"fillerOrigin":["Dominican Republic"],"binderOrigin":["Dominican Republic"],"color":"Colorado Claro / Natural","aromaProfileCommunity":{"weights":{"Cream":0.2,"Hazelnut":0.2,"Vanilla Bean":0.2,"Whisky":0.2,"White Chocolate":0.2},"numberOfVotes":0},"strength":"Mild To Medium","price":0,"additionalNotes":"C AO Eileen's Dream: quite possibly the most unique of CAO's Flavours. Comprised of a smooth Cameroon wrapper and mellow Dominican filler that have been infused with an explosion of ingredients including Irish whiskey, cream, coconut milk, hazelnut, white chocolate, almonds, cocoa, and vanilla bean. "}
