{"name":"Gran Habano - Azteca Fuerte - Torpedo","url":"https://www.cigarcentury.com/en/cigars/gran-habano-azteca-fuerte-torpedo","brand":"Gran Habano, Azteca Fuerte","series":"","diameter_mm":0,"ring":0,"length_mm":0,"length_inch":0,"format":"Torpedo / Piramide","maker":"G.R. Tabacaleras Co.","manufactureOrigin":"Honduras","isBoxpressed":false,"wrapperOrigin":["Mexican San Andres Maduro"],"fillerOrigin":["Nicaragua"],"binderOrigin":["Nicaragua"],"color":"Maduro","aromaProfileCommunity":{"weights":{"Cocoa":0.25,"Coffee":0.25,"Earth":0.25,"Pepper":0.25},"numberOfVotes":0},"strength":"Medium","price":0,"additionalNotes":"Gran Habano cigars are blended by George Rico and handcrafted in Honduras with the determined agenda of marrying rich flavors and marvelous construction with approachable prices. Gran Habano offers a steady and consistent variety of blends that true cigar nuts purchase by the box on a routine basis. Medium to full-bodied profiles that feature premium tobaccos with just the right amount of earthy spices are Gran Habano’s specialty."}
