{"name":"Foundry - Foundry - Cayley","url":"https://www.cigarcentury.com/en/cigars/foundry-foundry-cayley","brand":"Foundry, Foundry","series":"","diameter_mm":0,"ring":60,"length_mm":165,"length_inch":0,"format":"Perfecto / Double Figurado","maker":"General Cigars/ ST Group","manufactureOrigin":"Nicaragua","isBoxpressed":false,"wrapperOrigin":["Sungrown"],"fillerOrigin":["Various"],"binderOrigin":["Mixed"],"color":"Colorado Claro / Natural","aromaProfileCommunity":{"weights":{"Bread":0.3333333333333333,"Sweetness":0.3333333333333333,"Yeast":0.3333333333333333},"numberOfVotes":0},"strength":"Full","price":0,"additionalNotes":"Created by Michael Giannini of Team La Gloria Cubana, Foundry cigars are innovative, unique and creative. The original Foundry Cigar features a blend of five different tobaccos from four different countries wrapped in a Connecticut-seed wrapper aged for eight to ten years. An artisinal blend that will \n "}
