{"name":"1502 - Emerald - Toro","url":"https://www.cigarcentury.com/en/cigars/1502-emerald-toro","brand":"1502, Emerald","series":"","diameter_mm":0,"ring":50,"length_mm":152,"length_inch":0,"format":"Toro","maker":"Plasencia Cigars","manufactureOrigin":"Nicaragua","isBoxpressed":true,"wrapperOrigin":["Habano","Nicaraguan Corojo"],"fillerOrigin":["Nicaragua","Mexico"],"binderOrigin":["Nicaragua"],"color":"Colorado Claro / Natural","aromaProfileCommunity":{"weights":{"Cedar":0.2,"Chocolate":0.2,"Fruit":0.2,"Pepper":0.2,"Vanilla":0.2},"numberOfVotes":0},"strength":"Mild","price":0,"additionalNotes":"Our master blender had created this cigar from a combination of carefully selected and aged tobacco leaves. It has a subtle strength, with flavor and aroma that could only be achieved with the blend of Corojo Habano de Nicaragua, long fillers from San Andres – Mexico and fields from Estelí and Condega in Nicaragua.","specializedRatings":[{"who":"Cigar Coop","year":"2014","ratingOutOf100":92},{"who":"Cigar Coop","year":"2012","ratingOutOf100":91}]}
