{"name":"Caldwell - Eastern Standard - Dos Firmas - Piramide","url":"https://www.cigarcentury.com/en/cigars/caldwell-eastern-standard-dos-firmas-piramide","brand":"Caldwell, Eastern Standard, Dos Firmas","series":"","diameter_mm":0,"ring":50,"length_mm":130,"length_inch":0,"format":"Torpedo / Piramide","maker":"Tabacalera William Ventura","manufactureOrigin":"Dominican Republic","isBoxpressed":false,"wrapperOrigin":["USA Connecticut Shade"],"fillerOrigin":["N/A"],"binderOrigin":["N/A"],"color":"Claro","aromaProfileCommunity":{"weights":{"Cocoa":0.2,"Coffee with Cream":0.2,"Leather":0.2,"Orange":0.2,"Spices":0.2},"numberOfVotes":0},"strength":"Medium","price":0,"additionalNotes":"","specializedRatings":[{"who":"Cigar Coop","year":"2016","ratingOutOf100":93}]}
