{"name":"Dalay Sevilla Robusto Especial - Limitada Jar","url":"https://www.noblego.de/dalay-sevilla-robusto-especial-limitada-jar-zigarren/","brand":"Dalay","series":"","diameter_mm":21.4,"ring":54,"length_mm":158,"length_inch":0,"format":"Robusto","manufactureOrigin":"Dominikanische Republik","construction":"Longfiller","isBoxpressed":false,"wrapperOrigin":["Ecuador"],"WrapperTobaccoVariety":"Broadleaf","fillerOrigin":["Dominikanische Republik"],"binderOrigin":["Dominikanische Republik"],"aromaProfileManufacturer":["Fruchtig","Honig","Schokolade","Würzig"],"strength":"Medium","smokingDuration":"60 bis 90 Min","price":14.95,"additionalNotes":"Limited"}
