{"name":"Zino Platinum Scepter Stout","url":"https://www.noblego.de/zino-platinum-scepter-stout/","brand":"Zino","series":"Platinum Scepter","details":{"Fazit":"Die Zino Platinum Scepter Stout passt zu jeder Gelegenheit, bei der Zeit kein Hindernis darstellt. Ob Laie oder Aficionado, man kommt ob der Ausgeglichenheit und der feinen Entwicklung der Zigarre einfach mit ihr zurecht.\nDie Zino Platinum Scepter Stout ist eine innerlich und äußerlich schöne und wohlgenießbare Premiumzigarre.\nDazu passt ein leckerer Espresso, von Alkohol ist eher abzuraten, weil es den cremigen Smoke beeinflussen könnte.","Genuss":"Die Platinum Scepter Serie von Zino ist eine außergewöhnliche Reihe von Premiumzigarren, in der die Stout den Platz der Schönheit zusammen mit der Chubby einnimmt. Als Torpedo sowieso eine schöne Zigarre, schafft es die außergewöhnliche Qualität der Verarbeitung den Gesamteindruck noch zu erheben. Mit den knapp 18 Zentimetern Länge und einem Durchmesser von 21 Millimetern ist sie zudem eine stattliche Erscheinung, die einen 90 bis 100 minütigen entspannenden Smoke verspricht. Fruchtig-holzig und würzig mit einer sehr dezenten Schärfe ist die dennoch milde Stout ausgerichtet. Die Schärfe entwickelt sich leicht, ebenso wie die Aromenstärke leicht im Verlauf des Rauchvorgangs. Der Abbrand und das Zugverhalten sind exzellent."},"diameter_mm":21,"ring":53,"length_mm":178,"length_inch":0,"format":"Piramide","manufactureOrigin":"Dominikanische Republik","construction":"Longfiller","isBoxpressed":false,"wrapperOrigin":["Ecuador","Connecticut River Valley"],"fillerOrigin":["Dominikanische Republik","Peru"],"binderOrigin":["Connecticut"],"aromaProfileManufacturer":["Fruchtig","Holz","Nuss","Pfeffer"],"strength":"Medium","flavourStrength":"Medium-aromatisch","smokingDuration":"90 Min oder länger","price":16.05}
