{"name":"Aganorsa Leaf Signature Selection Robusto","url":"https://www.noblego.de/aganorsa-leaf-signature-selection-robusto-zigarren/","brand":"Aganorsa Leaf","series":"Signature Selection","details":{"Genussverlauf":"Das rotbraun schimmernde Deckblatt der Signature Selection Robusto von Aganorsa Leaf von der Sorte Corojo umschließt ein ebenfalls aus Nicaragua stammendes Corojo Umblatt. In der Einlage der mittelkräftigen Puro schlummern reife Corojo und Criollo 98 Tabake. Dieser raffinierte Blend sorgt für einen sehr cremigen Rauchgenuss mit schönen Aromen von Pfeffer, Kakao, Erde, Holz und Kaffee, die sich während des Rauchverlaufs sehr ausgewogen und abwechslungsreich präsentieren. Der Genießer kann sich aufgrund der immens hohen Verarbeitungsqualität dieser Zigarre entspannt zurücklehnen und sich ungestört auf ihr schmackhaftes Aromaspiel einlassen.","Resümee":"Eine Zigarre wie die Aganorsa Leaf Signature Selection Robusto sollte man unbedingt probieren. Die köstliche Puro überzeugt auf ganzer Linie und wird sich bei vielen Fans nicaraguanischer Tabakkultur einen Stammplatz im heimischen Humidor sichern."},"diameter_mm":20.6,"ring":52,"length_mm":127,"length_inch":0,"format":"Robusto","manufactureOrigin":"Nicaragua","isBoxpressed":false,"wrapperOrigin":["Nicaragua"],"fillerOrigin":["Nicaragua"],"binderOrigin":["Nicaragua"],"binderProperty":"Corojo","aromaProfileManufacturer":["Cremig","Eichenholz","Erdig","Kaffee","Kakao","Pfeffer","Würzig"],"strength":"Medium","flavourStrength":"Mild-aromatisch","smokingDuration":"60 bis 90 Min","price":10.9}
