{"name":"Nicarao Especial Gordo","url":"https://www.noblego.de/nicarao-especial-gordo/","brand":"Nicarao","series":"Edición Especial","diameter_mm":21,"ring":53,"length_mm":121,"length_inch":0,"format":"Robusto","manufactureOrigin":"Nicaragua","construction":"Longfiller","isBoxpressed":false,"wrapperOrigin":["Nicaragua"],"fillerOrigin":["Nicaragua"],"binderOrigin":["Nicaragua"],"aromaProfileManufacturer":["Erdig","Gewürze","Kaffee","Röstaromen"],"strength":"Medium","flavourStrength":"Medium-aromatisch","smokingDuration":"45 bis 90 Min","price":10.5}
