{"name":"Chinchalero Reserva D'Oro Perfecto","url":"https://www.noblego.de/chinchalero-reserva-d-oro-perfecto/","brand":"Chinchalero","series":"Reserva d'Oro","diameter_mm":20,"ring":50,"length_mm":128,"length_inch":0,"format":"Perfecto","manufactureOrigin":"Nicaragua","construction":"Longfiller","isBoxpressed":false,"wrapperOrigin":["Ecuador"],"fillerOrigin":["Honduras","Nicaragua"],"binderOrigin":["Honduras"],"wrapperType":"Connecticut Seed","aromaProfileManufacturer":["Gewürze","Orange","Pfeffer","Süß"],"strength":"Medium","flavourStrength":"Medium-aromatisch","smokingDuration":"45 bis 90 Min","price":3.8}
