{"name":"Casa de Nicaragua Corona","url":"https://www.noblego.de/casa-de-nicaragua-corona/","brand":"Casa de Nicaragua","series":"","diameter_mm":16,"ring":40,"length_mm":150,"length_inch":0,"format":"Corona","manufactureOrigin":"Nicaragua","construction":"Mediumfiller","isBoxpressed":false,"wrapperOrigin":["Ecuador"],"fillerOrigin":["Nicaragua"],"binderOrigin":["Indonesien"],"aromaProfileManufacturer":["Erdig","Fruchtig","Nuss"],"strength":"Medium","flavourStrength":"Medium-aromatisch","smokingDuration":"20 bis 45 Min","price":3.4}
