{"name":"Cain Sun Grown 660 Double Toro","url":"https://www.noblego.de/cain-sun-grown-660-double-toro/","brand":"Cain","series":"Sun Grown","diameter_mm":24,"ring":60,"length_mm":152,"length_inch":0,"format":"Double Toro","manufactureOrigin":"Nicaragua","construction":"Longfiller","isBoxpressed":false,"wrapperOrigin":["Nicaragua"],"fillerOrigin":["Nicaragua"],"binderOrigin":["Nicaragua"],"wrapperType":"Sungrown","aromaProfileManufacturer":["Nuss","Zedernholz"],"strength":"Stark","flavourStrength":"Medium-kräftig","smokingDuration":"45 bis 90 Min","price":9.9}
