{"name":"Gilbert de Montsalvat Signature Gran Robusto","url":"https://www.cigarworld.de/zigarren/dominikanische-republik/gilbert-de-montsalvat-signature-gran-robusto-90016401_51494","brand":"Gilbert de Montsalvat","series":"Gran Robusto","diameter_mm":21.4,"ring":54,"length_mm":139.7,"length_inch":5.5,"format":"Gran Robusto","maker":"Tabacalera Diaz Cabrera","manufactureOrigin":"","typeOfManufacturing":"TAM","isBoxpressed":false,"wrapperOrigin":["Dominikanische Republik"],"fillerOrigin":["Dominikanische Republik"],"binderOrigin":["Dominikanische Republik"],"isFlavoured":false,"aromaProfileCommunity":{"weights":{"Creme":0.15384615384615385,"Erde":0.038461538461538464,"Frucht":0.038461538461538464,"Gras":0.038461538461538464,"Holz":0.15384615384615385,"Kaffee":0.038461538461538464,"Leder":0.038461538461538464,"Nuss":0.07692307692307693,"Pfeffer":0.15384615384615385,"Schokolade":0.038461538461538464,"Süß":0.07692307692307693,"Toast":0.15384615384615385},"numberOfVotes":1},"price":12.5}
