{"name":"Ashton Aged Maduro No. 30 Lonsdale","url":"https://www.cigarworld.de/zigarren/dominikanische-republik/ashton-aged-maduro-no-30-lonsdale-90002426_9818","brand":"Ashton","series":"No. 30 Lonsdale","diameter_mm":17.1,"ring":43,"length_mm":168.2,"length_inch":6.625,"format":"","maker":"Tabacalera A. Fuente y Cia.","manufactureOrigin":"","typeOfManufacturing":"TAM","isBoxpressed":false,"wrapperOrigin":["USA"],"wrapperProperty":"Broadleaf","WrapperTobaccoVariety":"Connecticut","fillerOrigin":["Dominikanische Republik"],"fillerProperty":"Maduro","binderOrigin":["Dominikanische Republik"],"isFlavoured":false,"aromaProfileCommunity":{"weights":{"Creme":0.08333333333333333,"Erde":0.08333333333333333,"Frucht":0.041666666666666664,"Gras":0.041666666666666664,"Holz":0.08333333333333333,"Kaffee":0.0625,"Leder":0.08333333333333333,"Nuss":0.08333333333333333,"Pfeffer":0.10416666666666667,"Schokolade":0.125,"Süß":0.125,"Toast":0.08333333333333333},"numberOfVotes":7},"price":12.6}
