{"name":"Bossner Reserva (Nicaragua) Admiral","url":"https://www.cigarworld.de/zigarren/nicaragua/bossner-reserva-admiral-90002883_10662","brand":"Bossner","series":"Admiral","details":{"description":"\u003cp\u003eEin sehr gut gerollter Torpedotyp, am Kopfende in ein längeres Zöpfchen gedreht, die Brandseite ist mit dem Deckblatt (Colorado Maduro) leicht eingedreht, sehr guter kühler Zug, der Geschmack ist erdig-zedrig unterlegt, der ein samtiges Spiel von süsslich angedeuteter Würze und dezenter Bitterkeit entfaltet, eine sehr harmonisch komponierte Cigarre, die im Rauchverlauf auch an samtiger Dichte und Nachhaltigkeit im Geschmack gewinnt und dabei auch an Konzentration und Stärke im ausgewogenen Zusammenklang zunimmt, eine ausdrucksstarke Nicaragua-Cigarre. (European Cigar Cult Journal 2/2004)\u003cbr\u003e\u003c/br\u003e\u003cbr\u003e\u003c/br\u003e\u003cspan\u003eEine mittelstarke Cigarre, die mit ihrem würzigen Charakter kräftig erscheint. Im Rauch feinwürzig mit einer Zedernholznote. Im Aroma erinnert sie an Kaffee und Bittermandeln. Optimal im Zug. (Cigar 3/2005)\u003c/span\u003e\u003c/p\u003e\u003cdiv class=\"blanktag\" style=\"background: url('https://www.cigarworld.de/binary/shop/blank');\"\u003e\u003c/div\u003e"},"diameter_mm":23.799999999999997,"ring":60,"length_mm":139.7,"length_inch":5.5,"format":"","manufactureOrigin":"","typeOfManufacturing":"TAM","isBoxpressed":false,"wrapperOrigin":["Ecuador"],"WrapperTobaccoVariety":"H-2000","fillerOrigin":["Nicaragua"],"binderOrigin":["Nicaragua"],"isFlavoured":false,"price":15.7}
