{"name":"La Sirena  Robusto","url":"https://www.cigarworld.de/zigarren/nicaragua/la-sirena-robusto-90015860_44432","brand":"La Sirena","series":"Robusto","diameter_mm":19.8,"ring":50,"length_mm":127,"length_inch":5,"format":"Robustos","manufactureOrigin":"","isBoxpressed":false,"isFlavoured":false,"aromaProfileCommunity":{"weights":{"Creme":0.0625,"Erde":0.0625,"Frucht":0.09375,"Gras":0.03125,"Holz":0.09375,"Kaffee":0.09375,"Leder":0.0625,"Nuss":0.09375,"Pfeffer":0.09375,"Schokolade":0.125,"Süß":0.125,"Toast":0.0625},"numberOfVotes":1},"price":10.6}
