{"name":"Marca Fina Panama Edicion Limitada 2013 Corona Extra","url":"https://www.cigarworld.de/zigarren/panama/marca-fina-panama-edicion-limitada-2013-corona-extra-90004092_27980","brand":"Marca Fina","series":"Edicion Limitada 2013 Corona Extra","details":{"description":"\u003cp style=\"margin-bottom: 0cm; line-height: 100%;\"\u003eUnter den Zigarren der 2013er Sonderedition ist die Corona Extra die mit mittlerer Länge. Sie misst 13,8 Zentimeter, hat ein 48er Ringmaß und das Rauchen eine dieser Schönheiten dauert grob 40 Minuten. Handhabung und Zug dieser fair gehandelten Zigarre sind ebenfalls großartig.\u003c/p\u003e\u003cdiv class=\"blanktag\" style=\"background: url('https://www.cigarworld.de/binary/shop/blank');\"\u003e\u003c/div\u003e\n\u003cp style=\"margin-bottom: 0cm; line-height: 100%;\"\u003e \u003c/p\u003e\u003cdiv class=\"blanktag\" style=\"background: url('https://www.cigarworld.de/binary/shop/blank');\"\u003e\u003c/div\u003e\n\u003cp style=\"margin-bottom: 0cm; line-height: 100%;\"\u003eWie die anderen 2013-Zigarren in dieser Edition teilt die Corona Extra die Geschmacks-Charakteristika nicht mit den regulären Zigarren von Marca Fina Panama und wählt den Scherpunkt eher auch Erdigkeit, Leder und Kaffee.\u003c/p\u003e\u003cdiv class=\"blanktag\" style=\"background: url('https://www.cigarworld.de/binary/shop/blank');\"\u003e\u003c/div\u003e"},"diameter_mm":19.099999999999998,"ring":48,"length_mm":139.7,"length_inch":5.5,"format":"","manufactureOrigin":"","typeOfManufacturing":"TAF","isBoxpressed":false,"wrapperOrigin":["Panama"],"fillerOrigin":["Panama"],"binderOrigin":["Panama"],"isFlavoured":false,"aromaProfileCommunity":{"weights":{"Creme":0.05,"Erde":0.125,"Frucht":0.05,"Gras":0.1,"Holz":0.125,"Kaffee":0.05,"Leder":0.125,"Nuss":0.05,"Pfeffer":0.1,"Schokolade":0.05,"Süß":0.05,"Toast":0.125},"numberOfVotes":3},"price":3}
