{"name":"Privada Cigar Club  Hold Fast","url":"https://www.cigarworld.de/zigarren/nicaragua/privada-cigar-club-hold-fast-90016726_59349","brand":"Privada Cigar Club","series":"Hold Fast","diameter_mm":20.6,"ring":52,"length_mm":152.4,"length_inch":6,"format":"Toro","manufactureOrigin":"","typeOfManufacturing":"TAM","isBoxpressed":true,"WrapperTobaccoVariety":"H-2000","fillerOrigin":["Nicaragua"],"binderOrigin":["Nicaragua"],"isFlavoured":false,"aromaProfileCommunity":{"weights":{"Creme":0.043478260869565216,"Erde":0.17391304347826086,"Frucht":0.043478260869565216,"Gras":0.06521739130434782,"Holz":0.15217391304347827,"Kaffee":0.043478260869565216,"Leder":0.13043478260869565,"Nuss":0.043478260869565216,"Pfeffer":0.10869565217391304,"Schokolade":0.043478260869565216,"Süß":0.043478260869565216,"Toast":0.10869565217391304},"numberOfVotes":2},"price":11}
