{"name":"Marca Fina Nicaragua Piramide Breve","url":"https://www.cigarworld.de/zigarren/nicaragua/marca-fina-nicaragua-piramide-breve-90011406_27019","brand":"Marca Fina","series":"Piramide Breve","diameter_mm":20.6,"ring":52,"length_mm":101.6,"length_inch":4,"format":"Pirámides","manufactureOrigin":"","typeOfManufacturing":"TAF","isBoxpressed":false,"wrapperOrigin":["Nicaragua"],"fillerOrigin":["Nicaragua"],"binderOrigin":["Nicaragua"],"isFlavoured":false,"aromaProfileCommunity":{"weights":{"Creme":0.1276595744680851,"Erde":0.10638297872340426,"Frucht":0.06382978723404255,"Gras":0.06382978723404255,"Holz":0.0851063829787234,"Kaffee":0.0851063829787234,"Leder":0.06382978723404255,"Nuss":0.06382978723404255,"Pfeffer":0.0851063829787234,"Schokolade":0.10638297872340426,"Süß":0.06382978723404255,"Toast":0.0851063829787234},"numberOfVotes":9},"price":3.4}
