{"name":"Iberian Express Gibraltar Extra Torpedo","url":"https://www.cigargeeks.com/index.php?action=cigars;area=showcig;cigar_id=113623;t=Caldwell_Cigar_Co._Iberian_Express_Gibraltar_Extra_Torpedo","brand":"Caldwell Cigar Co.","series":"","diameter_mm":0,"ring":52,"length_mm":0,"length_inch":6.2,"format":"Torpedo","manufactureOrigin":"Dominican Republic","wrapperOrigin":["Ecuador","Habano"],"fillerOrigin":["Dominican Republic","Nicaragua"],"binderOrigin":["Dominican Republic"],"color":"Colorado","strength":"Medium","price":0}
