{"name":"Maduro Rabito Box-pressed (Privada CC Exclusive)","url":"https://www.cigargeeks.com/index.php?action=cigars;area=showcig;cigar_id=191877;t=Pier_28_Maduro_Rabito_Box-pressed_(Privada_CC_Exclusive)","brand":"Pier 28","series":"","diameter_mm":0,"ring":46,"length_mm":0,"length_inch":6.5,"format":"Corona Grande","manufactureOrigin":"Nicaragua","wrapperOrigin":["Mexico"],"fillerOrigin":["Nicaragua"],"binderOrigin":["Nicaragua"],"color":"Maduro","strength":"Medium","price":0,"additionalNotes":"https://privadacigarclub.com/product/pier-28-maduro-rabito-box-pressed-pcc-exclusive/"}
