{"name":"Mulligans Yacht Club Captain","url":"https://www.cigargeeks.com/index.php?action=cigars;area=showcig;cigar_id=207910;t=Rocky_Patel_Mulligans_Yacht_Club_Captain","brand":"Rocky Patel","series":"","diameter_mm":0,"ring":60,"length_mm":0,"length_inch":6,"format":"Toro Gordo","manufactureOrigin":"Undisclosed","wrapperOrigin":["Ecuador","Habano"],"fillerOrigin":["Dominican Republic","Nicaragua"],"binderOrigin":["Dominican Republic"],"color":"Colorado Maduro","strength":"Medium","price":0,"additionalNotes":"https://www.holts.com/cigars/all-cigar-brands/rocky-patel-mulligans-yacht-club.html"}
