{"name":"President Series Cordial (Privada Cigar Club Exc.)","url":"https://www.cigargeeks.com/index.php?action=cigars;area=showcig;cigar_id=195133;t=Montenegro_President_Series_Cordial_(Privada_Cigar_Club_Exc.)","brand":"Montenegro","series":"","diameter_mm":0,"ring":53,"length_mm":0,"length_inch":5.5,"format":"Robusto","manufactureOrigin":"Nicaragua","wrapperOrigin":["Ecuador","Habano"],"fillerOrigin":["Corojo","Criollo","Nicaragua"],"binderOrigin":["Corojo","Nicaragua"],"color":"Colorado","strength":"Medium-Full","price":0,"additionalNotes":"COTM selection from PCC for April '22.\n\nhttps://youtu.be/92ozQ6q_-WU?t=349\nhttps://privadacigarclub.com/shop/montenegro-president-series-cordial-aged-5-years/"}
