{"name":"Nude Phatties Maduro Big Gordo","url":"https://www.cigargeeks.com/index.php?action=cigars;area=showcig;cigar_id=40107;t=Cigar_King_Nude_Phatties_Maduro_Big_Gordo","brand":"Cigar King","series":"","diameter_mm":0,"ring":60,"length_mm":0,"length_inch":6,"format":"Toro Gordo","manufactureOrigin":"Nicaragua","fillerOrigin":["Honduras","Nicaragua"],"binderOrigin":["Honduras","Nicaragua"],"color":"Maduro","strength":"Medium","price":0,"additionalNotes":"http://www.cigarking.com/cigar-king-nude-phatties-maduro-big-gordo-5x56-bundle-20/\n\nAdmin Note:  The size on their website is a typo as its listed as the same size as the Lil Gordo.  I called and they said this one is 6x60 like the CT version. My info is correct"}
