{"name":"Protocol Eliot Ness Natural","url":"https://www.cigargeeks.com/index.php?action=cigars;area=showcig;cigar_id=194215;t=Cubariqueno_Cigar_Company_Protocol_Eliot_Ness_Natural","brand":"Cubariqueno Cigar Company","series":"","diameter_mm":0,"ring":52,"length_mm":0,"length_inch":6,"format":"Toro","manufactureOrigin":"Nicaragua","wrapperOrigin":["Habano","Nicaragua"],"fillerOrigin":["Criollo","Nicaragua"],"binderOrigin":["Habano","Nicaragua"],"color":"Colorado","strength":"Mild-Medium","price":0,"additionalNotes":"https://halfwheel.com/protocol-eliot-ness-natural/392953/"}
