{"name":"Tradicionales Panatela Natural","url":"https://www.cigargeeks.com/index.php?action=cigars;area=showcig;cigar_id=2623;t=Cuban_Cigar_Factory_Tradicionales_Panatela_Natural","brand":"Cuban Cigar Factory","series":"","diameter_mm":0,"ring":36,"length_mm":0,"length_inch":6.75,"format":"Panatela","manufactureOrigin":"United States","wrapperOrigin":["Connecticut"],"fillerOrigin":["Dominican Republic","Honduras","Nicaragua"],"binderOrigin":["Ecuador"],"color":"Colorado Maduro","strength":"Mild-Medium","price":0}
