{"name":"Classico Bucktown","url":"https://www.cigargeeks.com/index.php?action=cigars;area=showcig;cigar_id=91372;t=Macanudo_Classico_Bucktown","brand":"Macanudo","series":"","diameter_mm":0,"ring":52,"length_mm":0,"length_inch":6.125,"format":"Torpedo","manufactureOrigin":"Dominican Republic","wrapperOrigin":["Connecticut Shade"],"fillerOrigin":["Dominican Republic","Mexico"],"binderOrigin":["Mexico"],"color":"Claro","strength":"Mild-Medium","price":0,"additionalNotes":"Exclusive cigar for Arango Cigar Co"}
