{"name":"Dominican Sugar Tip Minatures Chocolate Macadamia","url":"https://www.cigargeeks.com/index.php?action=cigars;area=showcig;cigar_id=22764;t=Cool_Cat_Dominican_Sugar_Tip_Minatures_Chocolate_Macadamia","brand":"Cool Cat","series":"","diameter_mm":0,"ring":0,"length_mm":0,"length_inch":0,"format":"Cigarillo","manufactureOrigin":"United States","wrapperOrigin":["Dominican Republic"],"fillerOrigin":["Dominican Republic"],"binderOrigin":["Dominican Republic"],"color":"Colorado Maduro","strength":"Mild-Medium","price":0}
