{"name":"Serie R Black No. 56 Maduro","url":"https://www.cigargeeks.com/index.php?action=cigars;area=showcig;cigar_id=206257;t=La_Gloria_Cubana_Serie_R_Black_No._56_Maduro","brand":"La Gloria Cubana","series":"","diameter_mm":0,"ring":56,"length_mm":0,"length_inch":7,"format":"Long Gordo","manufactureOrigin":"Nicaragua","wrapperOrigin":["Connecticut Broadleaf"],"fillerOrigin":["Nicaragua"],"binderOrigin":["Nicaragua"],"color":"Maduro","strength":"Full","price":0,"additionalNotes":"https://www.cigarsinternational.com/p/la-gloria-cubana-serie-r-black-maduro-cigars/1508621/"}
