{"name":"Condega Serie S Churchill","url":"https://www.cigargeeks.com/index.php?action=cigars;area=showcig;cigar_id=191925;t=Casa_Fernandez_Condega_Serie_S_Churchill","brand":"Casa Fernandez","series":"","diameter_mm":0,"ring":50,"length_mm":0,"length_inch":7,"format":"Churchill","manufactureOrigin":"Nicaragua","wrapperOrigin":["Corojo","Nicaragua"],"fillerOrigin":["Corojo","Nicaragua"],"binderOrigin":["Nicaragua"],"color":"Colorado","strength":"Medium-Full","price":0,"additionalNotes":"https://www.smallbatchcigar.com/casa-fernandez-condega-churchill"}
