{"name":"Hors D'Age","url":"https://www.cigargeeks.com/index.php?action=cigars;area=showcig;cigar_id=189450;t=La_Aurora_Hors_DAge","brand":"La Aurora","series":"","diameter_mm":0,"ring":54,"length_mm":0,"length_inch":6,"format":"Toro","manufactureOrigin":"Dominican Republic","wrapperOrigin":["Ecuador"],"fillerOrigin":["Colombia","Dominican Republic","Nicaragua"],"binderOrigin":["Ecuador"],"color":"Colorado Maduro","strength":"Medium","price":0,"additionalNotes":"https://halfwheel.com/la-aurora-hors-dage-toro/285260"}
