{"name":"Cafe Cafe Cigarette","url":"https://www.cigargeeks.com/index.php?action=cigars;area=showcig;cigar_id=113340;t=Delicioso_(Cuban_Stock/_Crown_David)_Cafe_Cafe_Cigarette","brand":"Delicioso (Cuban Stock/ Crown David)","series":"","diameter_mm":0,"ring":32,"length_mm":0,"length_inch":4.5,"format":"Slim Panatela","manufactureOrigin":"Dominican Republic","wrapperOrigin":["Connecticut"],"fillerOrigin":["Dominican Republic"],"binderOrigin":["Dominican Republic"],"color":"Colorado Claro","strength":"Mild-Medium","price":0}
