{"name":"#62 Toro","url":"https://www.cigargeeks.com/index.php?action=cigars;area=showcig;cigar_id=191782;t=RVGN_#62_Toro","brand":"RVGN","series":"","diameter_mm":0,"ring":58,"length_mm":0,"length_inch":6,"format":"Toro Gordo","manufactureOrigin":"Dominican Republic","wrapperOrigin":["Ecuador"],"fillerOrigin":["Dominican Republic","Nicaragua","Pennsylvania"],"binderOrigin":["Criollo","Dominican Republic"],"color":"Colorado Claro","strength":"Medium","price":0,"additionalNotes":"https://www.smallbatchcigar.com/rvgn-cigars\nhttps://germanengineeredcigars.com/"}
