{"name":"Royal Selection Perfecto Long","url":"https://www.cigargeeks.com/index.php?action=cigars;area=showcig;cigar_id=12200;t=Cuban_Stock_(Crown_David)_Royal_Selection_Perfecto_Long","brand":"Cuban Stock (Crown David)","series":"","diameter_mm":0,"ring":48,"length_mm":0,"length_inch":7,"format":"Perfecto","manufactureOrigin":"Dominican Republic","wrapperOrigin":["Connecticut Shade","Ecuador"],"fillerOrigin":["Dominican Republic"],"binderOrigin":["Dominican Republic"],"color":"Claro","strength":"Medium-Full","price":0}
