{"name":"Send Nudes Vol. 1 Ecuadorian Connecticut Toro","url":"https://www.cigargeeks.com/index.php?action=cigars;area=showcig;cigar_id=195087;t=Room_101_Send_Nudes_Vol._1_Ecuadorian_Connecticut_Toro","brand":"Room 101","series":"","diameter_mm":0,"ring":50,"length_mm":0,"length_inch":6,"format":"Toro","manufactureOrigin":"Undisclosed","wrapperOrigin":["Connecticut Shade","Ecuador"],"fillerOrigin":["Nicaragua"],"binderOrigin":["Nicaragua"],"color":"Colorado Claro","price":0,"additionalNotes":"https://www.smallbatchcigar.com/room-101-send-nudes-vol-1-ecuadorian-connecticut-toro"}
