{"name":"The King Is Dead Escape Plan Drybeggar BP","url":"https://www.cigargeeks.com/index.php?action=cigars;area=showcig;cigar_id=194778;t=Caldwell_Cigar_Co._The_King_Is_Dead_Escape_Plan_Drybeggar_BP","brand":"Caldwell Cigar Co.","series":"","diameter_mm":0,"ring":52,"length_mm":0,"length_inch":6,"format":"Toro","manufactureOrigin":"Dominican Republic","wrapperOrigin":["Dominican Republic"],"fillerOrigin":["Dominican Republic","Nicaragua","Peru"],"binderOrigin":["Dominican Republic"],"color":"Colorado Maduro","strength":"Medium-Full","price":0,"additionalNotes":"https://halfwheel.com/caldwell-ships-the-king-is-dead-escape-plan/405746/\nhttps://atlanticcigar.com/caldwell-the-king-is-dead-escape-plan-drybeggar-52x6/"}
