{"name":"Coronas Superba Natural","url":"https://www.cigargeeks.com/index.php?action=cigars;area=showcig;cigar_id=24808;t=Lord_Beaconsfield_Coronas_Superba_Natural","brand":"Lord Beaconsfield","series":"","diameter_mm":0,"ring":24,"length_mm":0,"length_inch":6.25,"format":"Long Corona","manufactureOrigin":"Dominican Republic","wrapperOrigin":["Sumatra"],"fillerOrigin":["Caribbean Basin Cuban Seed"],"binderOrigin":["Homogenized Tobacco Leaf"],"color":"Colorado Maduro","strength":"Mild","price":0}
