{"name":"(White Box) Piramides Maduro","url":"https://www.cigargeeks.com/index.php?action=cigars;area=showcig;cigar_id=43527;t=La_Gloria_Cubana_(White_Box)_Piramides_Maduro","brand":"La Gloria Cubana","series":"","diameter_mm":0,"ring":60,"length_mm":0,"length_inch":7.25,"format":"Pyramid","manufactureOrigin":"Dominican Republic","wrapperOrigin":["Connecticut Broadleaf"],"fillerOrigin":["Dominican Republic","Nicaragua"],"binderOrigin":["Nicaragua"],"color":"Maduro","strength":"Medium-Full","price":0}
