{"name":"Presidente","url":"https://www.cigargeeks.com/index.php?action=cigars;area=showcig;cigar_id=3609;t=V_Centennial_(Tropical_Tobacco)_Presidente","brand":"V Centennial (Tropical Tobacco)","series":"","diameter_mm":0,"ring":50,"length_mm":0,"length_inch":8,"format":"Gigante","manufactureOrigin":"Honduras","wrapperOrigin":["Connecticut Shade","United States"],"fillerOrigin":["Dominican Republic","Honduras","Nicaragua"],"binderOrigin":["Mexico"],"color":"Claro","strength":"Medium","price":0}
