{"name":"Partageno Panatela \u0026 Corona Robust Corona Sumatra (430 - 5er Packung)","url":"https://www.cigarworld.de/zigarillos/sonstige-herkunft/partageno-panatela-corona-robust-corona-sumatra-430-5er-packung-30002375_3811","brand":"","series":"","diameter_mm":0,"ring":0,"length_mm":0,"length_inch":0,"format":"","manufactureOrigin":"","aromaProfileCommunity":{"weights":{"Creme":0.15,"Erde":0.1,"Frucht":0.125,"Gras":0.125,"Holz":0.075,"Kaffee":0.05,"Leder":0.05,"Nuss":0.05,"Pfeffer":0.025,"Schokolade":0.025,"Süß":0.15,"Toast":0.075},"numberOfVotes":3},"price":2.66}
