{"name":"Factory Overrun Dominikanische Republik PDR Maduro Torpedo Boxpressed (6.5x54 - BM30)","url":"https://www.cigarworld.de/zigarren/dominikanische-republik/factory-overrun-dominikanische-republik-pdr-maduro-torpedo-boxpressed-65x54-bm30-90013941_46779","brand":"Factory Overrun","series":"PDR Maduro Torpedo Boxpressed (6.5x54 - BM30)","diameter_mm":21.400000000000002,"ring":54,"length_mm":165.1,"length_inch":6.5,"format":"","manufactureOrigin":"","typeOfManufacturing":"TAM","isFlavoured":false,"price":3.85}
