{"name":"Casa Culinaria Esteli Corona","url":"https://www.cigarworld.de/zigarren/nicaragua/casa-culinaria-esteli-corona-90015690_42154","brand":"Casa Culinaria","series":"Corona","diameter_mm":15.9,"ring":40,"length_mm":136.5,"length_inch":5.375,"format":"","manufactureOrigin":"","typeOfManufacturing":"TAF","isBoxpressed":false,"wrapperOrigin":["Nicaragua"],"fillerOrigin":["Nicaragua"],"binderOrigin":["Nicaragua"],"isFlavoured":false,"aromaProfileCommunity":{"weights":{"Creme":0.08333333333333333,"Erde":0.041666666666666664,"Frucht":0.16666666666666666,"Gras":0.041666666666666664,"Holz":0.041666666666666664,"Kaffee":0.125,"Leder":0.041666666666666664,"Nuss":0.041666666666666664,"Pfeffer":0.125,"Schokolade":0.08333333333333333,"Süß":0.16666666666666666,"Toast":0.041666666666666664},"numberOfVotes":1},"price":2.8}
