{"name":"Kristoff It's a Girl / It's a Boy Zigarren Corona Boy (hellblau)","url":"https://www.cigarworld.de/zigarren/dominikanische-republik/kristoff-its-a-girl-its-a-boy-corona-boy-hellblau-90014201_31828","brand":"Kristoff","series":"Corona Boy (hellblau)","diameter_mm":16.7,"ring":42,"length_mm":139.7,"length_inch":5.5,"format":"","maker":"Charles Fairmorn S.A.","manufactureOrigin":"","typeOfManufacturing":"TAM","isBoxpressed":false,"wrapperOrigin":["Dominikanische Republik"],"fillerOrigin":["Dominikanische Republik"],"binderOrigin":["Dominikanische Republik"],"isFlavoured":false,"price":5}
