{"name":"Gurkha Pure Evil Robusto","url":"https://www.cigarworld.de/zigarren/nicaragua/gurkha-pure-evil-robusto-90016615_55056","brand":"Gurkha","series":"Robusto","diameter_mm":20.6,"ring":52,"length_mm":127,"length_inch":5,"format":"Robustos","maker":"American Caribbean Tobacco S.A.","manufactureOrigin":"","typeOfManufacturing":"TAM","isBoxpressed":false,"wrapperOrigin":["Ecuador"],"WrapperTobaccoVariety":"H-2000","fillerOrigin":["Nicaragua"],"binderOrigin":["Nicaragua"],"isFlavoured":false,"aromaProfileCommunity":{"weights":{"Creme":0.125,"Erde":0.025,"Frucht":0.05,"Gras":0.025,"Holz":0.05,"Kaffee":0.15,"Leder":0.1,"Nuss":0.125,"Pfeffer":0.075,"Schokolade":0.075,"Süß":0.125,"Toast":0.075},"numberOfVotes":2},"price":9}
