{"name":"La Rosa de Sandiego Zigarren Prensado Petit Bouquet","url":"https://www.cigarworld.de/zigarren/nicaragua/la-rosa-de-sandiego-prensado-petit-bouquet-90015569_43158","brand":"La Rosa de Sandiego","series":"Prensado Petit Bouquet","diameter_mm":23,"ring":58,"length_mm":130.2,"length_inch":5.125,"format":"","manufactureOrigin":"","isBoxpressed":false,"wrapperOrigin":["Mexiko"],"wrapperProperty":"Maduro","WrapperTobaccoVariety":"San Andrés","fillerOrigin":["Dominikanische Republik"],"fillerTobaccoVariety":"Esteli, Jalapa","binderOrigin":["Ecuador"],"isFlavoured":false,"aromaProfileCommunity":{"weights":{"Creme":0.125,"Erde":0.10714285714285714,"Frucht":0.07142857142857142,"Gras":0.017857142857142856,"Holz":0.07142857142857142,"Kaffee":0.125,"Leder":0.03571428571428571,"Nuss":0.07142857142857142,"Pfeffer":0.10714285714285714,"Schokolade":0.14285714285714285,"Süß":0.07142857142857142,"Toast":0.05357142857142857},"numberOfVotes":2},"price":7.8}
