{"name":"PDR El Vinyet Cuvee Especial RC 52 Robusto Clasico 2024","url":"https://www.cigarworld.de/zigarren/dominikanische-republik/pdr-el-vinyet-cuvee-especial-rc-52-robusto-clasico-2024-90016524_57999","brand":"PDR","series":"RC 52 Robusto Clasico 2024","diameter_mm":20.6,"ring":52,"length_mm":127,"length_inch":5,"format":"","maker":"PDR Cigars Tamboril","manufactureOrigin":"","typeOfManufacturing":"TAM","isBoxpressed":false,"wrapperOrigin":["Ecuador"],"WrapperTobaccoVariety":"H-2000","fillerOrigin":["Dominikanische Republik","USA"],"fillerTobaccoVariety":"Piloto","binderOrigin":["Indonesien"],"isFlavoured":false,"price":9.5}
