{"name":"Black Works Studio Intergalactic Robusto","url":"https://www.cigarworld.de/zigarren/nicaragua/black-works-studio-intergalactic-robusto-90016976_46172","brand":"Black Works Studio","series":"Robusto","diameter_mm":19.8,"ring":50,"length_mm":139.7,"length_inch":5.5,"format":"","maker":"Tabacalera Oveja Negra","manufactureOrigin":"","typeOfManufacturing":"TAM","isBoxpressed":false,"wrapperOrigin":["USA"],"wrapperProperty":"Broadleaf","WrapperTobaccoVariety":"Pennsylvania","fillerOrigin":["Nicaragua"],"binderOrigin":["Ecuador"],"isFlavoured":false,"price":13.9}
