{"name":"West Tampa Tobacco Company White Gigante","url":"https://www.noblego.de/west-tampa-tobacco-company-white-gigante-zigarren/","brand":"West Tampa Tobacco","series":"White","diameter_mm":23.8,"ring":60,"length_mm":152,"length_inch":0,"format":"Gigante","manufactureOrigin":"Nicaragua","construction":"Longfiller","isBoxpressed":false,"wrapperOrigin":["Ecuador"],"wrapperTobaccoVariety":["H2000"],"fillerOrigin":["Nicaragua"],"binderOrigin":["Nicaragua"],"aromaProfileManufacturer":["Brot","Cremig","Erdig","Pfeffer","Süß","Toast"],"strength":"Medium","smokingDuration":"60 bis 90 Min","price":11.5}
