{"name":"Vega Fina Short Robusto Tubo","url":"https://www.noblego.de/vega-fina-short-robusto-tubo/","brand":"Vega Fina","series":"Classic","diameter_mm":20,"ring":50,"length_mm":103,"length_inch":0,"format":"Short Robusto","manufactureOrigin":"Dominikanische Republik","construction":"Longfiller","isBoxpressed":false,"wrapperOrigin":["Ecuador"],"wrapperTobaccoVariety":["Connecticut","Shade"],"fillerOrigin":["Dominikanische Republik"],"binderOrigin":["Ecuador"],"aromaProfileManufacturer":["Cremig","Eichenholz","Nuss","Zedernholz"],"strength":"Mild","flavourStrength":"Medium-aromatisch","smokingDuration":"20 bis 45 Min","price":5.2}
