{"name":"Valentino Siesto Premium Maduro Toro","url":"https://www.noblego.de/valentino-siesto-premium-maduro-toro-zigarren/","brand":"Valentino Siesto","series":"","details":{"Genussverlauf":"Ausschließlich lang und auf den Punkt gereifte Tabake qualifizieren sich für den Blend der Premium Maduro Toro von Valentino Siesto. Ihr tiefbraunes Deckblatt kommt aus der mexikanischen Region San Andrés, die weltweit als eine der ersten Anlaufstellen für hochqualitative Tabake dieser Art bekannt ist. Ein dominikanisches Umblatt der Sorte Olor und erlesene Criollo sowie Corojo Einlagetabake der obersten Blattstufe (Ligero), ebenfalls in der Dominikanischen Republik gediehen, bilden den Rest des gehaltvollen Blends. Unter Feuer entwickelt das meisterlich gerollte Toro Format komplex auftretende Aromen von dunklem Holz, Kaffee und Zartbitterschokolade. Zu diesen gesellen sich angenehm feinwürzige Töne und eine stimmig austarierte Süße. Insgesamt erwartet den Genießer ein wunderbar cremig veranlagter Smoke von etwa 90 Minuten, der weder von schlechten Zug- oder Abbrandeigenschaften getrübt wird.","Resümee":"Die Valentino Siesto Premium Maduro Toro bereichert unser Sortiment seit Ende des Jahres 2022. Bei einer internen Hausverkostung der verschiedenen Blends des dominikanischen Premiumherstellers hat uns diese Zigarre besonders gut gefallen. Wir freuen uns daher sehr, Ihnen nun diesen feinen Genuss offerieren zu dürfen und wünschen viel Vergnügen dabei!"},"diameter_mm":20.6,"ring":52,"length_mm":152,"length_inch":0,"format":"Toro","manufactureOrigin":"Dominikanische Republik","construction":"Longfiller","isBoxpressed":false,"wrapperOrigin":["Mexico"],"WrapperTobaccoVariety":"San Andrés","fillerOrigin":["Dominikanische Republik"],"binderOrigin":["Dominikanische Republik"],"aromaProfileManufacturer":["Cremig","Holz","Kaffee","Schokolade","Süß"],"strength":"Medium","flavourStrength":"Mild-aromatisch","smokingDuration":"60 bis 90 Min","price":14.9}
